piblinky/__init__.py
piblinky/piblinky.py
piblinky-1.1.1.dist-info/licenses/LICENSE.txt
piblinky-1.1.1.dist-info/METADATA
piblinky-1.1.1.dist-info/WHEEL
piblinky-1.1.1.dist-info/top_level.txt
piblinky-1.1.1.dist-info/RECORD
