Metadata-Version: 2.4
Name: piblinky
Version: 1.1.1
Summary: piblinky - A threaded multiple LED driver for Raspberry Pi
Author-email: Chris Nelson <github@cjnaz.com>
License-Expression: MIT
Project-URL: repository, https://github.com/cjnaz/piblinky
Classifier: Topic :: Software Development :: Libraries :: Python Modules
Requires-Python: >=3.9
License-File: LICENSE.txt
Provides-Extra: gpio
Requires-Dist: RPi.GPIO; extra == "gpio"
Provides-Extra: pigpio
Requires-Dist: pigpio; extra == "pigpio"
Dynamic: license-file
